secondLaboratory/my.py
secondLaboratory-0.1.0.dist-info/METADATA
secondLaboratory-0.1.0.dist-info/WHEEL
secondLaboratory-0.1.0.dist-info/top_level.txt
secondLaboratory-0.1.0.dist-info/RECORD
