Metadata-Version: 2.1
Name: secondLaboratory
Version: 0.1.0
Summary: A example Python package
Home-page: UNKNOWN
Author: Anton Kupchik
Author-email: web_tattosha01@mail.ru
License: UNKNOWN
Platform: UNKNOWN
Requires: pandas
